SQLEvaluation/__init__.py
SQLEvaluation-1.1.11.dist-info/METADATA
SQLEvaluation-1.1.11.dist-info/WHEEL
SQLEvaluation-1.1.11.dist-info/top_level.txt
SQLEvaluation-1.1.11.dist-info/RECORD
