Metadata-Version: 2.1
Name: SQLEvaluation
Version: 1.1.11
Summary: sql evaluation
Home-page: UNKNOWN
Author: duang
Author-email: duangduang@gmail.com
License: UNKNOWN
Platform: UNKNOWN
Classifier: Programming Language :: Python :: 3
Classifier: License :: OSI Approved :: MIT License
Classifier: Operating System :: OS Independent
Requires-Python: >=3.6
